osmosis/__init__.py
osmosis/__main__.py
osmosis/cli.py
osmosis/version.py
osmosis/backend/__init__.py
osmosis/backend/config.py
osmosis/backend/fs.py
osmosis/backend/model.py
osmosis/backend/restoration.py
osmosis/backend/schedulers.py
osmosis/backend/server.py
osmosis/backend/utils.py
osmosis/backend/coreml/__init__.py
osmosis/backend/coreml/chunk_mlprogram.py
osmosis/backend/coreml/coreml_model.py
osmosis/backend/coreml/layer_norm.py
osmosis/backend/coreml/pipeline.py
osmosis/backend/coreml/torch2coreml.py
osmosis/backend/coreml/unet.py
osmosis/frontend/dist/index.html
osmosis/frontend/dist/assets/index-3055e4ea.css
osmosis/frontend/dist/assets/index-44d62d6f.js
osmosis-0.7.2.dist-info/LICENSE
osmosis-0.7.2.dist-info/METADATA
osmosis-0.7.2.dist-info/WHEEL
osmosis-0.7.2.dist-info/entry_points.txt
osmosis-0.7.2.dist-info/top_level.txt
osmosis-0.7.2.dist-info/RECORD
