Metadata-Version: 2.1
Name: osmosis
Version: 0.7.2
Summary: An experimental Stable Diffusion frontend
Author-email: Ryan Cao <hello@ryanccn.dev>
Classifier: Development Status :: 3 - Alpha
Classifier: Environment :: GPU
Classifier: Environment :: GPU :: NVIDIA CUDA
Classifier: Environment :: MacOS X
Classifier: Environment :: Web Environment
Classifier: Framework :: Flask
Classifier: Intended Audience :: End Users/Desktop
Classifier: Intended Audience :: Science/Research
Classifier: License :: OSI Approved :: GNU Affero General Public License v3
Classifier: Natural Language :: English
Classifier: Operating System :: MacOS
Classifier: Operating System :: Microsoft :: Windows
Classifier: Operating System :: POSIX :: Linux
Classifier: Programming Language :: JavaScript
Classifier: Programming Language :: Python :: 3.9
Classifier: Programming Language :: Python :: 3.10
Classifier: Topic :: Multimedia :: Graphics
Classifier: Topic :: Scientific/Engineering :: Artificial Intelligence
Requires-Python: <3.11,>=3.9
License-File: LICENSE
Requires-Dist: diffusers[torch] (~=0.14)
Requires-Dist: safetensors
Requires-Dist: compel (~=1.0.2)
Requires-Dist: transformers
Requires-Dist: accelerate
Requires-Dist: flask (~=2.2.3)
Requires-Dist: flask-socketio (~=5.3.2)
Requires-Dist: eventlet
Requires-Dist: torch (>=2.0.0)
Requires-Dist: omegaconf
Requires-Dist: realesrgan (~=0.3)
Requires-Dist: gfpgan (~=1.3)
Requires-Dist: click (>=8.1)
Requires-Dist: rich
Requires-Dist: tqdm
Requires-Dist: psutil
Requires-Dist: coremltools ; sys_platform == "darwin"
Provides-Extra: dev
Requires-Dist: black ; extra == 'dev'
Provides-Extra: xformers
Requires-Dist: xformers (~=0.0.16) ; (sys_platform != "darwin") and extra == 'xformers'
Requires-Dist: triton ; (sys_platform == "linux") and extra == 'xformers'
